{
    "congruence": {
        "0": {},
        "group_602420180": {
            "123": [
                "456"
            ]
        },
        "group_810830220": {
            "唉": [
                "唉牛魔"
            ],
            "哎": [
                "哎牛魔"
            ]
        }
    },
    "include": {
        "0": {},
        "group_810830220": {
            "土唐唐": [
                "土唐唐怎么你了"
            ],
            "go批": [
                "不看mygo的人注定要度过相对失败的一生"
            ],
            "月批": [
                "䏔"
            ]
        }
    },
    "regex": {
        "0": {},
        "group_810830220": {
            "唉，": [
                "唉牛魔"
            ]
        }
    }
}